MANIFEST.in
Readme.md
requirements.txt
setup.py
gmusicSyncRatings/__init__.py
gmusicSyncRatings/__main__.py
gmusicSyncRatings/args.py
gmusicSyncRatings/rating_sync.py
gmusicSyncRatings/test.py
gmusic_rating_sync.egg-info/PKG-INFO
gmusic_rating_sync.egg-info/SOURCES.txt
gmusic_rating_sync.egg-info/dependency_links.txt
gmusic_rating_sync.egg-info/entry_points.txt
gmusic_rating_sync.egg-info/not-zip-safe
gmusic_rating_sync.egg-info/requires.txt
gmusic_rating_sync.egg-info/top_level.txt