Metadata-Version: 1.1
Name: gmusic-rating-sync
Version: 1.1.2
Summary: Syncs your iTunes rating to Google Music. Supports the 5 start rating system
Home-page: https://github.com/Bilalh/gmusic-sync-ratings
Author: Bilal Syed Hussain
Author-email: bilalshussain@gmail.com
License: Apache License 2.0
Keywords: Google Music,Google Play,iTunes,ratings,music
Platform: UNKNOWN
Classifier: License :: OSI Approved
Classifier: License :: OSI Approved :: Apache Software License
Classifier: Topic :: Utilities
Classifier: Topic :: Multimedia :: Sound/Audio
Classifier: Topic :: Multimedia :: Sound/Audio :: Editors
Classifier: Programming Language :: Python
Classifier: Programming Language :: Python :: 2
Classifier: Programming Language :: Python :: 2.7
